deepbiome/__init__.py
deepbiome/_version.py
deepbiome/build_network.py
deepbiome/configuration.py
deepbiome/deepbiome.py
deepbiome/logging_daily.py
deepbiome/loss_and_metric.py
deepbiome/readers.py
deepbiome/utils.py
deepbiome/tests/__init__.py
deepbiome/tests/conftest.py
deepbiome/tests/test_deepmicrobiome.py
deepbiome/tests/data/ages.csv
deepbiome/tests/data/classification_deep_l1_network_info.cfg
deepbiome/tests/data/classification_deep_l1_path_info.cfg
deepbiome/tests/data/classification_deep_network_info.cfg
deepbiome/tests/data/classification_deep_path_info.cfg
deepbiome/tests/data/classification_idx.csv
deepbiome/tests/data/classification_network_info.cfg
deepbiome/tests/data/classification_path_info.cfg
deepbiome/tests/data/classification_real_test_evaluation.npy
deepbiome/tests/data/classification_real_train_evaluation.npy
deepbiome/tests/data/classification_y.csv
deepbiome/tests/data/ethnicity.csv
deepbiome/tests/data/gcount_list.csv
deepbiome/tests/data/gender.csv
deepbiome/tests/data/genus48_dic.csv
deepbiome/tests/data/genus48_dic_tmp.csv
deepbiome/tests/data/log_info.yaml
deepbiome/tests/data/onefile_classification_y.csv
deepbiome/tests/data/onefile_idx.csv
deepbiome/tests/data/onefile_regression_y.csv
deepbiome/tests/data/onefile_x.csv
deepbiome/tests/data/prediction_classification_network_info.cfg
deepbiome/tests/data/prediction_classification_path_info.cfg
deepbiome/tests/data/prediction_regression_network_info.cfg
deepbiome/tests/data/prediction_regression_path_info.cfg
deepbiome/tests/data/regression_deep_l1_network_info.cfg
deepbiome/tests/data/regression_deep_l1_path_info.cfg
deepbiome/tests/data/regression_deep_network_info.cfg
deepbiome/tests/data/regression_deep_path_info.cfg
deepbiome/tests/data/regression_idx.csv
deepbiome/tests/data/regression_network_info.cfg
deepbiome/tests/data/regression_path_info.cfg
deepbiome/tests/data/regression_real_test_evaluation.npy
deepbiome/tests/data/regression_real_train_evaluation.npy
deepbiome-1.0.1.dist-info/AUTHORS.rst
deepbiome-1.0.1.dist-info/LICENSE
deepbiome-1.0.1.dist-info/METADATA
deepbiome-1.0.1.dist-info/WHEEL
deepbiome-1.0.1.dist-info/entry_points.txt
deepbiome-1.0.1.dist-info/top_level.txt
deepbiome-1.0.1.dist-info/RECORD
