Metadata-Version: 2.1
Name: deepbiome
Version: 1.0.1
Summary: Deep Learning package using the phylogenetic tree information for microbiome data analysis.
Home-page: https://github.com/Young-won/deepbiome
Author: Youngwon Choi
Author-email: youngwon08@gmail.com
License: BSD (3-clause)
Platform: UNKNOWN
Classifier: Development Status :: 2 - Pre-Alpha
Classifier: Natural Language :: English
Classifier: Programming Language :: Python :: 3
Requires-Python: >=3.5
Requires-Dist: keras
Requires-Dist: tensorflow (>=1.12)
Requires-Dist: numpy (>=1.12)
Requires-Dist: pandas
Requires-Dist: sklearn
Requires-Dist: PyQt5 (==5.10)
Requires-Dist: ete3
